pytimesheet/__init__.py
pytimesheet/cli.py
pytimesheet/config.ini
pytimesheet/generate.py
pytimesheet/storage.py
pytimesheet/utils.py
pytimesheet/template/logo.png
pytimesheet/template/stundenzettel_template.tex
pytimesheet-0.0.12.dist-info/DESCRIPTION.rst
pytimesheet-0.0.12.dist-info/METADATA
pytimesheet-0.0.12.dist-info/RECORD
pytimesheet-0.0.12.dist-info/WHEEL
pytimesheet-0.0.12.dist-info/entry_points.txt
pytimesheet-0.0.12.dist-info/metadata.json
pytimesheet-0.0.12.dist-info/top_level.txt
